fill_voids/__init__.py
fill_voids/fill_voids.cpython-38-aarch64-linux-gnu.so
fill_voids/fill_voids.hpp
fill_voids/fill_voids.pyi
fill_voids/fill_voids.pyx
fill_voids/libdivide.h
fill_voids-2.1.1.dist-info/AUTHORS
fill_voids-2.1.1.dist-info/COPYING
fill_voids-2.1.1.dist-info/COPYING.LESSER
fill_voids-2.1.1.dist-info/METADATA
fill_voids-2.1.1.dist-info/WHEEL
fill_voids-2.1.1.dist-info/pbr.json
fill_voids-2.1.1.dist-info/top_level.txt
fill_voids-2.1.1.dist-info/RECORD
