Metadata-Version: 2.1
Name: fill_voids
Version: 2.1.1
Summary: Fill voids in 3D binary images fast.
Home-page: https://github.com/seung-lab/fill_voids/
Author: William Silversmith
Author-email: ws9@princeton.edu
License: LGPL-3.0-or-later
Classifier: Intended Audience :: Developers
Classifier: Development Status :: 5 - Production/Stable
Classifier: Programming Language :: Python :: 3
Classifier: Programming Language :: Python :: 3.9
Classifier: Programming Language :: Python :: 3.10
Classifier: Programming Language :: Python :: 3.11
Classifier: Programming Language :: Python :: 3.12
Classifier: Programming Language :: Python :: 3.13
Classifier: Topic :: Scientific/Engineering
License-File: COPYING
License-File: COPYING.LESSER
License-File: AUTHORS
Requires-Dist: numpy
Requires-Dist: fastremap
